[
	{
		"attack": 1,
		"back_link": "33001b",
		"code": "33001a",
		"defense": 2,
		"double_sided": true,
		"faction_code": "hero",
		"hand_size": "5",
		"health": 10,
		"is_unique": true,
		"meta": {
			"colors": [
				"#0e4681",
				"#e8b844",
				"#0e294a",
				"#fffffd"
			]
		},
		"name": "Cyclops",
		"octgn_id": "7da2a29c-3abd-4e3b-b36e-9f140c033001",
		"pack_code": "cyclops",
		"position": 1,
		"quantity": 1,
		"set_code": "cyclops",
		"text": "<i>Optic Blast</i> - <b>Action</b> <i>(attack)</i>: Spend one resource of any type → deal 3 damage to an enemy with an upgrade attached. (Limit once per round).",
		"thwart": 2,
		"traits": "X-Men.",
		"type_code": "hero"
	},
	{
		"code": "33001b",
		"double_sided": true,
		"faction_code": "hero",
		"hand_size": "6",
		"health": 10,
		"hidden": true,
		"is_unique": true,
		"name": "Scott Summers",
		"octgn_id": "7da2a29c-3abd-4e3b-b36e-9f140c033001",
		"pack_code": "cyclops",
		"position": 1,
		"quantity": 1,
		"recover": 3,
		"set_code": "cyclops",
		"text": "You may include [[X-MEN]] allies from any aspect in your deck.\n<i>Constant Training</i> - <b>Action</b>: Search your deck for a [[TACTIC]] upgrade and add it to your hand. (Limit once per round).",
		"traits": "Mutant.",
		"type_code": "alter_ego"
	},
	{
		"attack": 2,
		"code": "33002",
		"cost": 3,
		"deck_limit": 1,
		"faction_code": "hero",
		"health": 3,
		"is_unique": true,
		"name": "Phoenix",
		"octgn_id": "7da2a29c-3abd-4e3b-b36e-9f140c033002",
		"pack_code": "cyclops",
		"position": 2,
		"quantity": 1,
		"resource_wild": 1,
		"set_code": "cyclops",
		"set_position": 1,
		"subname": "Jean Grey",
		"text": "<b>Response</b>: After Phoenix enters play, choose a Cyclops card in your discard pile and add it to your hand.",
		"thwart": 2,
		"traits": "Psionic. X-Men.",
		"type_code": "ally"
	},
	{
		"code": "33003",
		"cost": 2,
		"deck_limit": 1,
		"faction_code": "hero",
		"is_unique": true,
		"name": "Ruby Quartz Visor",
		"octgn_id": "7da2a29c-3abd-4e3b-b36e-9f140c033003",
		"pack_code": "cyclops",
		"position": 3,
		"quantity": 1,
		"resource_physical": "1",
		"set_code": "cyclops",
		"set_position": 2,
		"text": "<b>Hero Resource</b>: Exhaust this card → generate a [energy] resource for your <i>\"Optic Blast\"</i> ability. That attack gains piercing and ranged.",
		"traits": "Item.",
		"type_code": "upgrade"
	},
	{
		"code": "33004",
		"cost": 1,
		"deck_limit": 1,
		"faction_code": "hero",
		"is_unique": true,
		"name": "Field Commander",
		"octgn_id": "7da2a29c-3abd-4e3b-b36e-9f140c033004",
		"pack_code": "cyclops",
		"position": 4,
		"quantity": 1,
		"resource_physical": "1",
		"set_code": "cyclops",
		"set_position": 3,
		"text": "You take the first turn during player phase. <i>(When your turn is done, play proceeds in player order, starting with the first player. You do not take another turn.)</i>\nEach Cyclops upgrade attached to a minion loses the temporary keyword.",
		"traits": "Title.",
		"type_code": "upgrade"
	},
	{
		"code": "33005",
		"cost": 1,
		"deck_limit": 2,
		"faction_code": "hero",
		"name": "Exploit Weakness",
		"octgn_id": "7da2a29c-3abd-4e3b-b36e-9f140c033005",
		"pack_code": "cyclops",
		"position": 5,
		"quantity": 2,
		"resource_physical": "1",
		"set_code": "cyclops",
		"set_position": 4,
		"text": "Attach to an enemy. Max 1 per enemy.\nTemporary.\nIncrease the amount of damage attached enemy takes from each attack by 1.",
		"traits": "Tactic.",
		"type_code": "upgrade"
	},
	{
		"code": "33006",
		"cost": 0,
		"deck_limit": 2,
		"faction_code": "hero",
		"name": "Practiced Defense",
		"octgn_id": "7da2a29c-3abd-4e3b-b36e-9f140c033006",
		"pack_code": "cyclops",
		"position": 6,
		"quantity": 2,
		"resource_energy": 1,
		"set_code": "cyclops",
		"set_position": 6,
		"text": "Attach to an enemy. Max 1 per enemy.\nTemporary.\nAttached enemy gets -1 ATK.",
		"traits": "Tactic.",
		"type_code": "upgrade"
	},
	{
		"code": "33007",
		"cost": 0,
		"deck_limit": 2,
		"faction_code": "hero",
		"name": "Priority Target",
		"octgn_id": "7da2a29c-3abd-4e3b-b36e-9f140c033007",
		"pack_code": "cyclops",
		"position": 7,
		"quantity": 2,
		"resource_mental": "1",
		"set_code": "cyclops",
		"set_position": 8,
		"text": "Attach to an enemy. Max 1 per enemy.\nTemporary.\n<b>Interrupt</b>: When attached enemy is defeated, the player who defeated it draws 2 cards.",
		"traits": "Tactic.",
		"type_code": "upgrade"
	},
	{
		"code": "33008",
		"cost": 1,
		"deck_limit": 1,
		"faction_code": "hero",
		"name": "Full Blast",
		"octgn_id": "7da2a29c-3abd-4e3b-b36e-9f140c033008",
		"pack_code": "cyclops",
		"position": 8,
		"quantity": 1,
		"resource_physical": "1",
		"set_code": "cyclops",
		"set_position": 10,
		"text": "<b>Hero Interrupt</b>: When you use your <i>\"Optic Blast\"</i> ability, exhaust Cyclops → this attack deals 8 additionnal damage and gains overkill.",
		"traits": "Superpower.",
		"type_code": "event"
	},
	{
		"code": "33009",
		"cost": 2,
		"deck_limit": 2,
		"faction_code": "hero",
		"name": "Rocket Beam",
		"octgn_id": "7da2a29c-3abd-4e3b-b36e-9f140c033009",
		"pack_code": "cyclops",
		"position": 9,
		"quantity": 2,
		"resource_energy": 1,
		"set_code": "cyclops",
		"set_position": 11,
		"text": "<b>Hero Action</b> <i>(attack)</i>: Deal 3 damage to an enemy. Deal 3 damage to an enemy with an upgrade attached.",
		"traits": "Attack. Superpower.",
		"type_code": "event"
	},
	{
		"code": "33010",
		"cost": 2,
		"deck_limit": 3,
		"faction_code": "hero",
		"name": "Tactical Brillance",
		"octgn_id": "7da2a29c-3abd-4e3b-b36e-9f140c033010",
		"pack_code": "cyclops",
		"position": 10,
		"quantity": 3,
		"resource_mental": "1",
		"set_code": "cyclops",
		"set_position": 13,
		"text": "<b>Hero Action</b> <i>(thwart)</i>: Dremove 3 threat from a scheme. Choose a [[TACTIC]] card in your discard pile and add it to your hand.",
		"traits": "Thwart.",
		"type_code": "event"
	},
	{
		"attack": 2,
		"code": "33011",
		"cost": 4,
		"deck_limit": 1,
		"faction_code": "leadership",
		"health": 3,
		"is_unique": true,
		"name": "Beast",
		"octgn_id": "7da2a29c-3abd-4e3b-b36e-9f140c033011",
		"pack_code": "cyclops",
		"position": 11,
		"quantity": 1,
		"resource_mental": "1",
		"subname": "Hank Mccoy",
		"text": "<b>Response</b>: After Beast enters play, search your deck and discard pile for a resource card and add it to your hand. <i>(Shuffle.)</i>",
		"thwart": 2,
		"traits": "Genius. X-Men.",
		"type_code": "ally"
	},
	{
		"attack": 1,
		"code": "33012",
		"cost": 3,
		"deck_limit": 1,
		"faction_code": "aggression",
		"health": 3,
		"is_unique": true,
		"name": "Dust",
		"octgn_id": "7da2a29c-3abd-4e3b-b36e-9f140c033012",
		"pack_code": "cyclops",
		"position": 12,
		"quantity": 1,
		"resource_energy": 1,
		"subname": "Sooraya Qadir",
		"text": "[star] <b>Interrupt</b>: When Dust attacks a minion, she attacks each minion in play. Dust takes +1 consequential damage ([consequential]) after this attack.",
		"thwart": 1,
		"traits": "X-Men.",
		"type_code": "ally"
	},
	{
		"attack": 3,
		"code": "33013",
		"cost": 4,
		"deck_limit": 1,
		"faction_code": "protection",
		"health": 6,
		"is_unique": true,
		"name": "Rockslide",
		"octgn_id": "7da2a29c-3abd-4e3b-b36e-9f140c033013",
		"pack_code": "cyclops",
		"position": 13,
		"quantity": 1,
		"resource_physical": "1",
		"subname": "Santo Vaccarro",
		"text": "Retaliate 1.",
		"thwart": 1,
		"traits": "X-Men.",
		"type_code": "ally"
	},
	{
		"attack": 0,
		"code": "33014",
		"cost": 3,
		"deck_limit": 1,
		"faction_code": "justice",
		"health": 2,
		"is_unique": true,
		"name": "Blindfold",
		"octgn_id": "7da2a29c-3abd-4e3b-b36e-9f140c033014",
		"pack_code": "cyclops",
		"position": 14,
		"quantity": 1,
		"resource_physical": "1",
		"subname": "Ruth Aldine",
		"text": "<b>Response</b>: After Blindfold enters play, look at the top 5 cards of the encounter deck. Discard 1 of those cards and put the rest back in the same order.",
		"thwart": 2,
		"traits": "Psionic. X-Men.",
		"type_code": "ally"
	},
	{
		"code": "33015",
		"cost": 1,
		"deck_limit": 3,
		"faction_code": "leadership",
		"name": "Danger Room Training",
		"octgn_id": "7da2a29c-3abd-4e3b-b36e-9f140c033015",
		"pack_code": "cyclops",
		"position": 15,
		"quantity": 3,
		"resource_mental": "1",
		"text": "Attach to an [[X-MEN]] ally. Max 1 [[TRAINING]] upgrade per ally.\nAttached ally gets +1 THW, +1 ATK and +1 hot point.",
		"traits": "Training.",
		"type_code": "upgrade"
	},
	{
		"code": "33016",
		"cost": 0,
		"deck_limit": 3,
		"faction_code": "leadership",
		"name": "Coordinated Attack",
		"octgn_id": "7da2a29c-3abd-4e3b-b36e-9f140c033016",
		"pack_code": "cyclops",
		"position": 16,
		"quantity": 3,
		"resource_physical": "1",
		"text": "Attach to an minion. Max 1 per minion.\nEach ally takes -1 consequential damage ([consequential]) when attacking attached minion.",
		"traits": "Tactic.",
		"type_code": "upgrade"
	},
	{
		"code": "33017",
		"duplicate_of": "06032",
		"octgn_id": "7da2a29c-3abd-4e3b-b36e-9f140c033017",
		"pack_code": "cyclops",
		"position": 17,
		"quantity": 3
	},
	{
		"code": "33018",
		"deck_limit": 2,
		"faction_code": "leadership",
		"name": "Effective Leadership",
		"octgn_id": "7da2a29c-3abd-4e3b-b36e-9f140c033018",
		"pack_code": "cyclops",
		"position": 18,
		"quantity": 2,
		"resource_wild": 1,
		"text": "Max 2 per deck.\n<b>Interrupt</b>: When you spend this card to play an ally, that ally gets +1 THW and +1 ATK until the end of the phase.",
		"type_code": "resource"
	},
	{
		"attack": 2,
		"code": "33019",
		"cost": 3,
		"deck_limit": 1,
		"faction_code": "basic",
		"health": 3,
		"is_unique": true,
		"name": "Angel",
		"octgn_id": "7da2a29c-3abd-4e3b-b36e-9f140c033019",
		"pack_code": "cyclops",
		"position": 19,
		"quantity": 1,
		"resource_mental": "1",
		"subname": "Warren Worthington III",
		"text": "Reduce the cost to play Angel by 1 if your identity has the [[MUTANT]] or [[X-MEN]] trait.",
		"thwart": 1,
		"traits": "Aerial. X-Men.",
		"type_code": "ally"
	},
	{
		"code": "33020",
		"cost": 2,
		"deck_limit": 1,
		"faction_code": "basic",
		"is_unique": true,
		"name": "Utopia",
		"octgn_id": "7da2a29c-3abd-4e3b-b36e-9f140c033020",
		"pack_code": "cyclops",
		"position": 20,
		"quantity": 1,
		"resource_physical": "1",
		"text": "If each of your allies has the [[X-MEN]] trait, increase your ally limit by 1.\n<b>Response:</b> After an [[X-MEN]] ally enters play, exhaust Utopia -> ready an [[X-MEN]] character.",
		"traits": "Location. X-Men.",
		"type_code": "support"
	},
	{
		"code": "33021",
		"cost": 2,
		"deck_limit": 1,
		"faction_code": "basic",
		"is_unique": true,
		"name": "Danger Room",
		"octgn_id": "7da2a29c-3abd-4e3b-b36e-9f140c033021",
		"pack_code": "cyclops",
		"position": 21,
		"quantity": 1,
		"resource_energy": 1,
		"text": "<b>Alter-Ego Response</b>: After an [[X-MEN]] ally enters play, exhaust Danger Room → search your deck and discard pile for a [[TRAINING]] upgrade and attach it to that ally. Any player whose alter-ego has the [[MUTANT]] trait may trigger this ability.",
		"traits": "Location. X-Men.",
		"type_code": "support"
	},
	{
		"code": "33022",
		"cost": 0,
		"deck_limit": 3,
		"faction_code": "basic",
		"name": "Game Time",
		"octgn_id": "7da2a29c-3abd-4e3b-b36e-9f140c033022",
		"pack_code": "cyclops",
		"position": 22,
		"quantity": 3,
		"resource_energy": 1,
		"text": "<b>Hero Action</b>: Choose an ally with a [[TRAINING]] upgrade attached → ready that ally and heal 1 damage from it.",
		"traits": "Tactic.",
		"type_code": "event"
	},
	{
		"code": "33023",
		"cost": 2,
		"deck_limit": 1,
		"faction_code": "basic",
		"name": "Psychic Rapport",
		"octgn_id": "7da2a29c-3abd-4e3b-b36e-9f140c033023",
		"pack_code": "cyclops",
		"position": 23,
		"quantity": 1,
		"resource_energy": 1,
		"text": "Team-Up (Cyclops and Phoenix). Max 1 per deck.\n<b>Hero Action</b>: Ready Cyclops and Phoenix. Choose to either return a Cyclops card from your discard pile to your hand or place 2 power counters on Phoenix Force.",
		"type_code": "event"
	},
	{
		"code": "33024",
		"duplicate_of": "01088",
		"pack_code": "cyclops",
		"position": 24,
		"quantity": 1
	},
	{
		"code": "33025",
		"duplicate_of": "01089",
		"pack_code": "cyclops",
		"position": 25,
		"quantity": 1
	},
	{
		"code": "33026",
		"duplicate_of": "01090",
		"pack_code": "cyclops",
		"position": 26,
		"quantity": 1
	},
	{
		"code": "33032",
		"cost": 0,
		"deck_limit": 3,
		"faction_code": "aggression",
		"name": "Marked",
		"octgn_id": "7da2a29c-3abd-4e3b-b36e-9f140c033032",
		"pack_code": "cyclops",
		"position": 32,
		"quantity": 3,
		"text": "Attach to an minion. Max 1 per minion.\nAttacks against attached minion gain overkill.",
		"traits": "Tactic.",
		"type_code": "upgrade"
	},
	{
		"code": "33033",
		"cost": 0,
		"deck_limit": 3,
		"faction_code": "justice",
		"name": "Befuddle",
		"octgn_id": "7da2a29c-3abd-4e3b-b36e-9f140c033033",
		"pack_code": "cyclops",
		"position": 33,
		"quantity": 3,
		"text": "Attach to an minion. Max 1 per minion.\n<b>Interrupt</b>: When a character makes a basic attack against attached minion, that character uses THW instead of their ATK.",
		"traits": "Tactic.",
		"type_code": "upgrade"
	},
	{
		"code": "33034",
		"cost": 0,
		"deck_limit": 3,
		"faction_code": "protection",
		"name": "Pinned Down",
		"octgn_id": "7da2a29c-3abd-4e3b-b36e-9f140c033034",
		"pack_code": "cyclops",
		"position": 34,
		"quantity": 3,
		"text": "Attach to an minion. Max 1 per minion.\nAttached minion gets -2 ATK.",
		"traits": "Tactic.",
		"type_code": "upgrade"
	},
	{
		"code": "33035",
		"cost": 0,
		"deck_limit": 3,
		"faction_code": "basic",
		"name": "Honorary X-Men",
		"octgn_id": "7da2a29c-3abd-4e3b-b36e-9f140c033035",
		"pack_code": "cyclops",
		"position": 35,
		"quantity": 3,
		"text": "Play only if your identity has the [[X-MEN]] trait.\nAttach to a friendly character.\nAttached character gets +1 hit point and gains the [[X-MEN]] trait.",
		"traits": "Title.",
		"type_code": "upgrade"
	}
]
