[
    {
        "attack": 1,
        "back_link": "47001b",
        "code": "47001a",
        "defense": 2,
        "faction_code": "hero",
        "flavor": "\"You should know I get torqued when people ignore me!\"",
        "hand_size": 5,
        "health": 9,
        "illustrator": "Andrea Di Vito & Laura Villari",
        "is_unique": true,
        "meta": {
            "colors": [
                "#48499b",
                "#fdf242",
                "#da549f",
                "#fffffd"
            ],
            "offset": "-38px -33px"
        },
        "name": "Jubilee",
        "octgn_id": "2bb9367c-944e-4475-b643-6a84c3047001",
        "pack_code": "jubilee",
        "position": 1,
        "quantity": 1,
        "set_code": "jubilee",
        "text": "<i>\"Like, totally!\"</i> \u2014 <b>Resource</b>: Exhaust Jubilee \u2192 generate a [wild] resource.",
        "thwart": 1,
        "traits": "X-Men.",
        "type_code": "hero"
    },
    {
        "code": "47001b",
        "faction_code": "hero",
        "flavor": "\"This place was sooo much cooler when I lived here!\"",
        "hand_size": 6,
        "health": 9,
        "hidden": true,
        "illustrator": "Andrea Di Vito & Laura Villari",
        "is_unique": true,
        "name": "Jubilation Lee",
        "octgn_id": "2bb9367c-944e-4475-b643-6a84c3047001",
        "pack_code": "jubilee",
        "position": 1,
        "quantity": 1,
        "recover": 3,
        "set_code": "jubilee",
        "text": "<i>Mall Rat</i> \u2014 <b>Action</b>: Search your deck for the Shopping Spree player side scheme and put it into play. (Limit once per phase.)",
        "traits": "Mutant.",
        "type_code": "alter_ego"
    },
    {
        "attack": 3,
        "attack_cost": 2,
        "attack_star": true,
        "code": "47002",
        "cost": 4,
        "deck_limit": 1,
        "faction_code": "hero",
        "flavor": "\"Pipe down, squirt. We ain't here on holiday!\"",
        "health": 4,
        "is_unique": true,
        "name": "Wolverine",
        "octgn_id": "2bb9367c-944e-4475-b643-6a84c3047002",
        "pack_code": "jubilee",
        "position": 2,
        "quantity": 1,
        "resource_wild": 1,
        "set_code": "jubilee",
        "set_position": 1,
        "subname": "Logan",
        "text": "[star] Wolverine's attacks gain piercing.\n<b>Response</b>: After you change to alter-ego form, heal 3 damage from Wolverine.",
        "thwart": 1,
        "thwart_cost": 1,
        "traits": "X-Men.",
        "type_code": "ally"
    },
    {
        "base_threat": 2,
        "base_threat_fixed": true,
        "code": "47003",
        "cost": 0,
        "deck_limit": 1,
        "faction_code": "hero",
        "illustrator": "Lorenzo Di Santo",
        "is_unique": true,
        "name": "Shopping Spree",
        "octgn_id": "2bb9367c-944e-4475-b643-6a84c3047003",
        "pack_code": "jubilee",
        "position": 3,
        "quantity": 1,
        "resource_wild": 1,
        "set_code": "jubilee",
        "set_position": 2,
        "text": "Threat cannot be removed from this scheme by heroes or allies.\n<b>Alter-Ego Action</b>: Exhaust your identity \u2192 remove 1 threat from here. Any player may trigger this ability.\n<b>When Defeated</b>: The player who defeated this scheme searches their deck and discard pile for an [[Item]] card and puts it into play.",
        "type_code": "player_side_scheme"
    },
    {
        "code": "47004",
        "cost": 2,
        "deck_limit": 1,
        "faction_code": "hero",
        "is_unique": true,
        "name": "Jubilee's Coat",
        "octgn_id": "2bb9367c-944e-4475-b643-6a84c3047004",
        "pack_code": "jubilee",
        "position": 4,
        "quantity": 1,
        "resource_wild": 1,
        "set_code": "jubilee",
        "set_position": 3,
        "text": "Jubilee gets +1 THW.\n<b>Hero Response</b> <i>(thwart)</i>: After you play a [[Thwart]] event, exhaust Jubilee's Coat and choose a scheme \u2192 remove 1 threat from that scheme for each different resource type used to pay for that event.",
        "traits": "Item.",
        "type_code": "upgrade"
    },
    {
        "code": "47005",
        "cost": 2,
        "deck_limit": 1,
        "faction_code": "hero",
        "illustrator": "Bruno Frenda",
        "is_unique": true,
        "name": "Jubilee's Sunglasses",
        "octgn_id": "2bb9367c-944e-4475-b643-6a84c3047005",
        "pack_code": "jubilee",
        "position": 5,
        "quantity": 1,
        "resource_wild": 1,
        "set_code": "jubilee",
        "set_position": 4,
        "text": "Jubilee gets +1 ATK.\n<b>Hero Response</b> <i>(attack)</i>: After you play an [[Attack]] event, exhaust Jubilee's Sunglasses and choose an enemy \u2192 deal 1 damage to that enemy for each different resource type used to pay for that event.",
        "traits": "Item.",
        "type_code": "upgrade"
    },
    {
        "code": "47006",
        "cost": 3,
        "deck_limit": 1,
        "faction_code": "hero",
        "illustrator": "Denis Medri",
        "name": "Blinding Flash",
        "octgn_id": "2bb9367c-944e-4475-b643-6a84c3047006",
        "pack_code": "jubilee",
        "position": 6,
        "quantity": 1,
        "resource_wild": 1,
        "set_code": "jubilee",
        "set_position": 5,
        "text": "<b>Hero Action</b>: Choose X enemies, where X is the number of different resource types <i>([energy], [mental], [physical], and [wild])</i> used to pay for this event. Stun and confuse each chosen enemy.",
        "traits": "Superpower.",
        "type_code": "event"
    },
    {
        "code": "47007a",
        "cost": 2,
        "deck_limit": 1,
        "faction_code": "hero",
        "flavor": "\"Where do they find all these henchmen? Must be a discount store somewhere.\" \u2014Jubilee",
        "name": "Firecracker",
        "octgn_id": "2bb9367c-944e-4475-b643-6a84c3047007",
        "pack_code": "jubilee",
        "position": 7,
        "quantity": 1,
        "resource_energy": 1,
        "set_code": "jubilee",
        "set_position": 6,
        "text": "<b>Hero Action</b> <i>(attack)</i>: Deal 4 damage to an enemy. If you paid for this card using 2 different resource types, stun that enemy.",
        "traits": "Attack. Superpower.",
        "type_code": "event"
    },
    {
        "code": "47007b",
        "cost": 2,
        "deck_limit": 1,
        "faction_code": "hero",
        "flavor": "\"Where do they find all these henchmen? Must be a discount store somewhere.\" \u2014Jubilee",
        "name": "Firecracker",
        "octgn_id": "2bb9367c-944e-4475-b643-6a84c3047008",
        "pack_code": "jubilee",
        "position": 7,
        "quantity": 1,
        "resource_mental": 1,
        "set_code": "jubilee",
        "set_position": 7,
        "text": "<b>Hero Action</b> <i>(attack)</i>: Deal 4 damage to an enemy. If you paid for this card using 2 different resource types, stun that enemy.",
        "traits": "Attack. Superpower.",
        "type_code": "event"
    },
    {
        "code": "47007c",
        "cost": 2,
        "deck_limit": 1,
        "faction_code": "hero",
        "flavor": "\"Where do they find all these henchmen? Must be a discount store somewhere.\" \u2014Jubilee",
        "name": "Firecracker",
        "octgn_id": "2bb9367c-944e-4475-b643-6a84c3047009",
        "pack_code": "jubilee",
        "position": 7,
        "quantity": 1,
        "resource_physical": 1,
        "set_code": "jubilee",
        "set_position": 8,
        "text": "<b>Hero Action</b> <i>(attack)</i>: Deal 4 damage to an enemy. If you paid for this card using 2 different resource types, stun that enemy.",
        "traits": "Attack. Superpower.",
        "type_code": "event"
    },
    {
        "code": "47008a",
        "cost": 2,
        "deck_limit": 1,
        "faction_code": "hero",
        "flavor": "\"That's enough for me, folks. I'm out!\" \u2014Jubilee",
        "name": "Flash of Light",
        "octgn_id": "2bb9367c-944e-4475-b643-6a84c3047010",
        "pack_code": "jubilee",
        "position": 8,
        "quantity": 1,
        "resource_energy": 1,
        "set_code": "jubilee",
        "set_position": 9,
        "text": "<b>Hero Action</b> <i>(thwart)</i>: Remove 3 threat from a scheme. If you paid for this card using 2 different resource types, confuse an enemy.",
        "traits": "Superpower. Thwart.",
        "type_code": "event"
    },
    {
        "code": "47008b",
        "cost": 2,
        "deck_limit": 1,
        "faction_code": "hero",
        "flavor": "\"That's enough for me, folks. I'm out!\" \u2014Jubilee",
        "name": "Flash of Light",
        "octgn_id": "2bb9367c-944e-4475-b643-6a84c3047011",
        "pack_code": "jubilee",
        "position": 8,
        "quantity": 1,
        "resource_mental": 1,
        "set_code": "jubilee",
        "set_position": 10,
        "text": "<b>Hero Action</b> <i>(thwart)</i>: Remove 3 threat from a scheme. If you paid for this card using 2 different resource types, confuse an enemy.",
        "traits": "Superpower. Thwart.",
        "type_code": "event"
    },
    {
        "code": "47008c",
        "cost": 2,
        "deck_limit": 1,
        "faction_code": "hero",
        "flavor": "\"That's enough for me, folks. I'm out!\" \u2014Jubilee",
        "name": "Flash of Light",
        "octgn_id": "2bb9367c-944e-4475-b643-6a84c3047012",
        "pack_code": "jubilee",
        "position": 8,
        "quantity": 1,
        "resource_physical": 1,
        "set_code": "jubilee",
        "set_position": 11,
        "text": "<b>Hero Action</b> <i>(thwart)</i>: Remove 3 threat from a scheme. If you paid for this card using 2 different resource types, confuse an enemy.",
        "traits": "Superpower. Thwart.",
        "type_code": "event"
    },
    {
        "code": "47009",
        "cost": 3,
        "deck_limit": 1,
        "faction_code": "hero",
        "name": "Grande Finale",
        "octgn_id": "2bb9367c-944e-4475-b643-6a84c3047013",
        "pack_code": "jubilee",
        "position": 9,
        "quantity": 1,
        "resource_wild": 1,
        "set_code": "jubilee",
        "set_position": 12,
        "text": "<b>Hero Action</b> <i>(attack)</i>: Deal 2 damage to an enemy. For each different resource type <i>([energy], [mental], [physical], and [wild])</i> you used to pay for this card, choose an enemy and deal 2 damage to it.",
        "traits": "Attack. Superpower.",
        "type_code": "event"
    },
    {
        "code": "47010a",
        "deck_limit": 1,
        "faction_code": "hero",
        "flavor": "\"Cover your eyes, team! It's about to get lit!\" \u2014Jubilee",
        "name": "Plasmoid Energy",
        "octgn_id": "2bb9367c-944e-4475-b643-6a84c3047014",
        "pack_code": "jubilee",
        "position": 10,
        "quantity": 1,
        "resource_energy": 1,
        "resource_mental": 1,
        "set_code": "jubilee",
        "set_position": 13,
        "type_code": "resource"
    },
    {
        "code": "47010b",
        "deck_limit": 1,
        "faction_code": "hero",
        "flavor": "\"Cover your eyes, team! It's about to get lit!\" \u2014Jubilee",
        "name": "Plasmoid Energy",
        "octgn_id": "2bb9367c-944e-4475-b643-6a84c3047015",
        "pack_code": "jubilee",
        "position": 10,
        "quantity": 1,
        "resource_energy": 1,
        "resource_physical": 1,
        "set_code": "jubilee",
        "set_position": 14,
        "type_code": "resource"
    },
    {
        "code": "47010c",
        "deck_limit": 1,
        "faction_code": "hero",
        "flavor": "\"Cover your eyes, team! It's about to get lit!\" \u2014Jubilee",
        "name": "Plasmoid Energy",
        "octgn_id": "2bb9367c-944e-4475-b643-6a84c3047016",
        "pack_code": "jubilee",
        "position": 10,
        "quantity": 1,
        "resource_mental": 1,
        "resource_physical": 1,
        "set_code": "jubilee",
        "set_position": 15,
        "type_code": "resource"
    },
    {
        "attack": 2,
        "attack_cost": 1,
        "attack_star": true,
        "code": "47011",
        "cost": 4,
        "deck_limit": 1,
        "faction_code": "justice",
        "flavor": "\"Don't worry about me, luv \u2014 I've got this.\"",
        "health": 3,
        "is_unique": true,
        "name": "Chamber",
        "octgn_id": "2bb9367c-944e-4475-b643-6a84c3047017",
        "pack_code": "jubilee",
        "position": 11,
        "quantity": 1,
        "resource_energy": 1,
        "subname": "Jono Starsmore",
        "text": "[star] Chamber takes -1 consequential damage ([cost]) after he attacks a confused enemy.",
        "thwart": 2,
        "thwart_cost": 1,
        "traits": "Psionic. X-Men.",
        "type_code": "ally"
    },
    {
        "attack": 2,
        "attack_cost": 1,
        "attack_star": true,
        "code": "47012",
        "cost": 4,
        "deck_limit": 1,
        "faction_code": "justice",
        "health": 3,
        "is_unique": true,
        "name": "Husk",
        "octgn_id": "2bb9367c-944e-4475-b643-6a84c3047018",
        "pack_code": "jubilee",
        "position": 12,
        "quantity": 1,
        "resource_physical": 1,
        "subname": "Paige Guthrie",
        "text": "[star] <b>Interrupt</b>: When Husk uses a basic power, spend up to 3 resources \u2192 if you spent at least 1:\n[energy] \u2014 Husk gets +1 to that power for this use.\n[mental] \u2014 Heal 1 damage from Husk.\n[physical] \u2014 Ready Husk after this use.",
        "thwart": 2,
        "thwart_cost": 1,
        "thwart_star": true,
        "traits": "X-Men.",
        "type_code": "ally"
    },
    {
        "code": "47013",
        "cost": 1,
        "deck_limit": 3,
        "faction_code": "justice",
        "flavor": "\"The name's 'Patch.' Just 'Patch.'\" \u2014Wolverine",
        "illustrator": "Andrea Di Vito & Laura Villari",
        "name": "Disguise",
        "octgn_id": "2bb9367c-944e-4475-b643-6a84c3047019",
        "pack_code": "jubilee",
        "position": 13,
        "quantity": 3,
        "resource_mental": 1,
        "text": "Play under any player's control. Max 1 per player.\n<b>Action</b> <i>(thwart)</i>: Exhaust Disguise and your identity \u2192 remove 2 threat from a scheme.",
        "traits": "Item.",
        "type_code": "upgrade"
    },
    {
        "code": "47014",
        "cost": 3,
        "deck_limit": 3,
        "faction_code": "justice",
        "flavor": "\"You hurt self-friends! No you will pay!\" \u2014Warlock",
        "name": "Waylay",
        "octgn_id": "2bb9367c-944e-4475-b643-6a84c3047020",
        "pack_code": "jubilee",
        "position": 14,
        "quantity": 3,
        "resource_physical": 1,
        "text": "<b>Hero Response</b> <i>(attack)</i>: After your hero thwarts, deal 4 damage to an enemy (7 damage instead if that thwart removed the last threat from a scheme).",
        "traits": "Attack.",
        "type_code": "event"
    },
    {
        "code": "47015",
        "cost": 3,
        "deck_limit": 3,
        "faction_code": "justice",
        "flavor": "\"You should be proud, Rogue\u2014me and Glob worked this out ahead of time!\" \u2014Anole",
        "name": "Three Steps Ahead",
        "octgn_id": "2bb9367c-944e-4475-b643-6a84c3047021",
        "pack_code": "jubilee",
        "position": 15,
        "quantity": 3,
        "resource_mental": 1,
        "text": "<b>Hero Action</b> <i>(thwart)</i>: For each different resource type <i>([energy], [mental], [physical], and [wild])</i> you used to pay for this card, choose a scheme and remove 2 threat from it.",
        "traits": "Thwart.",
        "type_code": "event"
    },
    {
        "base_threat": 3,
        "code": "47016",
        "cost": 0,
        "deck_limit": 1,
        "faction_code": "justice",
        "is_unique": true,
        "name": "Generation X",
        "octgn_id": "2bb9367c-944e-4475-b643-6a84c3047022",
        "pack_code": "jubilee",
        "position": 16,
        "quantity": 1,
        "resource_energy": 1,
        "text": "Victory 0.\nEach [[X-Men]] character gets +1 THW while making a basic thwart against this scheme.\n<b>When Defeated</b>: Each player may search their deck and discard pile for an identity-specific event and add it to their hand. <i>(Shuffle.)</i>",
        "type_code": "player_side_scheme"
    },
    {
        "code": "47017",
        "duplicate_of": "01062",
        "pack_code": "jubilee",
        "position": 17,
        "quantity": 2
    },
    {
        "attack": 1,
        "attack_cost": 1,
        "code": "47018",
        "cost": 3,
        "deck_limit": 1,
        "faction_code": "basic",
        "health": 3,
        "is_unique": true,
        "name": "Synch",
        "octgn_id": "2bb9367c-944e-4475-b643-6a84c3047024",
        "pack_code": "jubilee",
        "position": 18,
        "quantity": 1,
        "resource_energy": 1,
        "subname": "Everett Thomas",
        "text": "Play only if your identity has the [[X-Men]] trait.\n<b>Interrupt</b>: When you use a basic power, exhaust Synch \u2192 you get +1 to that power for this use.",
        "thwart": 1,
        "thwart_cost": 1,
        "traits": "X-Men.",
        "type_code": "ally"
    },
    {
        "code": "47019",
        "cost": 2,
        "deck_limit": 3,
        "faction_code": "basic",
        "name": "Cell Phone",
        "octgn_id": "2bb9367c-944e-4475-b643-6a84c3047025",
        "pack_code": "jubilee",
        "position": 19,
        "quantity": 3,
        "resource_energy": 1,
        "text": "Uses (3 charge counters).\n<b>Action</b>: Exhaust Cell Phone, remove 1 charge counter from here, and choose a player \u2192 that player makes a basic attack or thwart with a character they control. That character gets +1 THW and +1 ATK for this use.",
        "traits": "Item.",
        "type_code": "upgrade"
    },
    {
        "code": "47020",
        "duplicate_of": "38019",
        "pack_code": "jubilee",
        "position": 20,
        "quantity": 3
    },
    {
        "code": "47021",
        "cost": 3,
        "deck_limit": 3,
        "faction_code": "basic",
        "illustrator": "Allie Preswick",
        "name": "Multitalented",
        "octgn_id": "2bb9367c-944e-4475-b643-6a84c3047027",
        "pack_code": "jubilee",
        "position": 21,
        "quantity": 3,
        "resource_physical": 1,
        "text": "<b>Hero Action</b> <i>(attack/thwart)</i>: If you paid for this event using at least 1:\n[physical] \u2014 Deal 2 damage to an enemy.\n[mental] \u2014 Remove 2 threat from a scheme.\n[energy] \u2014 Heal 2 damage from your identity.",
        "traits": "Attack. Thwart.",
        "type_code": "event"
    },
    {
        "code": "47022",
        "cost": 2,
        "deck_limit": 1,
        "faction_code": "basic",
        "illustrator": "Facundo Moyano",
        "name": "Unlikely Duo",
        "octgn_id": "2bb9367c-944e-4475-b643-6a84c3047028",
        "pack_code": "jubilee",
        "position": 22,
        "quantity": 2,
        "resource_wild": 1,
        "text": "Team-Up (Jubilee and Wolverine). Max 1 per deck.\n<b>Hero Action</b> <i>(attack)</i>: Confuse an enemy. Deal 4 damage to a confused enemy.",
        "traits": "Attack.",
        "type_code": "event"
    },
    {
        "code": "47028",
        "cost": 3,
        "deck_limit": 3,
        "faction_code": "leadership",
        "name": "Mutant Mayhem",
        "octgn_id": "2bb9367c-944e-4475-b643-6a84c3047034",
        "pack_code": "jubilee",
        "position": 28,
        "quantity": 3,
        "resource_energy": 1,
        "text": "Alliance.\n<b>Hero Action</b>: Choose an [[X-Force]] ally and an [[X-Men]] ally and return them to their owners' hands \u2192 those players play those allies, ignoring their resource costs.",
        "type_code": "event"
    },
    {
        "code": "47029",
        "cost": 2,
        "deck_limit": 3,
        "faction_code": "protection",
        "name": "Serve and Protect",
        "octgn_id": "2bb9367c-944e-4475-b643-6a84c3047035",
        "pack_code": "jubilee",
        "position": 29,
        "quantity": 3,
        "resource_mental": 1,
        "text": "Alliance.\n<b>Hero Interrupt</b>: When any amount of threat would be placed on the main scheme, exhaust an [[X-Force]] character and an [[X-Men]] character \u2192 prevent that threat and give each of those characters a tough status card.",
        "type_code": "event"
    }
]
