[
	{
		"attack": 3,
		"attack_cost": 1,
		"code": "06011",
		"cost": 6,
		"deck_limit": 1,
		"faction_code": "aggression",
		"flavor": "Whatever Thor can do, Hercules can accomplish more mightily!",
		"health": 4,
		"is_unique": true,
		"name": "Hercules",
		"pack_code": "thor",
		"position": 11,
		"quantity": 1,
		"resource_physical": 1,
		"text": "Reduce the cost to play Hercules by 1 for each minion engaged with you.",
		"thwart": 1,
		"thwart_cost": 1,
		"traits": "Avenger. Olympus.",
		"type_code": "ally"
	},{
		"attack": 2,
		"attack_cost": 1,
		"code": "06012",
		"cost": 3,
		"deck_limit": 1,
		"faction_code": "aggression",
		"flavor": "I am Valkyrie, shieldmaiden of Asgard.",
		"health": 3,
		"is_unique": true,
		"name": "Valkyrie",
		"pack_code": "thor",
		"position": 12,
		"quantity": 1,
		"resource_energy": 1,
		"text": "<b>Response:</b> After Valkyrie enters play, deal 2 damage to a minion (3 damage instead if you paid for this card using a [energy] resource).",
		"thwart": 1,
		"thwart_cost": 1,
		"traits": "Asgard. Avenger.",
		"type_code": "ally"
	},
	{
		"code": "06019",
		"cost": 1,
		"deck_limit": 1,
		"faction_code": "aggression",
		"name": "Jarnbjorn",
		"pack_code": "thor",
		"position": 19,
		"quantity": 1,
		"resource_physical": 1,
		"text": "Restricted. \n <b>Response:</b> After your hero attacks an enemy, spend a [physical] resource → deal 2 damage to an enemy.",
		"traits": "Asgard. Weapon",
		"type_code": "upgrade"
	},
	{
		"code": "06032",
		"cost": 0,
		"deck_limit": 3,
		"faction_code": "leadership",
		"flavor": "",
		"name": "Teamwork",
		"pack_code": "thor",
		"position": 32,
		"quantity": 3,
		"resource_energy": 1,
		"text": "<b>Hero Interrupt</b> When you use your basic thwart power (THW) or basic attack power (ATK), exhaust an ally you control → add that ally's matching power to your hero's power for this use.",
		"traits": "Tactic.",
		"type_code": "event"
	}
]